wave_form_provider/__init__.py
wave_form_provider/providers/__init__.py
wave_form_provider/providers/cartesia_provider.py
wave_form_provider/providers/chatterbox_provider.py
wave_form_provider/providers/elevenlabs_provider.py
wave_form_provider/providers/google_gemini_provider.py
wave_form_provider/providers/hume_provider.py
wave_form_provider/providers/inworld_provider.py
wave_form_provider/providers/openai_provider.py
wave_form_provider/providers/orpheus_provider.py
wave_form_provider/providers/tts_provider.py
wave_form_provider/util/util.py
wave_form_provider-0.1.3.dist-info/licenses/LICENSE
wave_form_provider-0.1.3.dist-info/METADATA
wave_form_provider-0.1.3.dist-info/WHEEL
wave_form_provider-0.1.3.dist-info/top_level.txt
wave_form_provider-0.1.3.dist-info/RECORD
