Metadata-Version: 2.4
Name: wave-form-provider
Version: 0.1.3
Summary: A universal TTS provider interface with unified expressive markup syntax
Author-email: Prince Hodonou <prince.hodonou0@gmail.com>
License: MIT
Keywords: tts,text-to-speech,voice,ai,cartesia,elevenlabs,hume,inworld
Classifier: Development Status :: 3 - Alpha
Classifier: Intended Audience :: Developers
Classifier: License :: OSI Approved :: MIT License
Classifier: Programming Language :: Python :: 3
Classifier: Programming Language :: Python :: 3.8
Classifier: Programming Language :: Python :: 3.9
Classifier: Programming Language :: Python :: 3.10
Classifier: Programming Language :: Python :: 3.11
Classifier: Programming Language :: Python :: 3.12
Requires-Python: >=3.8
License-File: LICENSE
Requires-Dist: elevenlabs>=2.22.1
Requires-Dist: google-cloud-texttospeech>=2.33.0
Requires-Dist: hume>=0.13.4
Requires-Dist: openai>=2.7.2
Requires-Dist: replicate>=1.0.7
Requires-Dist: requests>=2.32.5
Requires-Dist: pydantic>=2.12.4
Provides-Extra: dev
Requires-Dist: pytest>=9.0.0; extra == "dev"
Requires-Dist: mypy>=1.18.2; extra == "dev"
Dynamic: license-file
